kubedownscaler/__init__.py
kubedownscaler/main.py
kubedownscaler-0.4.2.dist-info/METADATA
kubedownscaler-0.4.2.dist-info/WHEEL
kubedownscaler-0.4.2.dist-info/entry_points.txt
kubedownscaler-0.4.2.dist-info/RECORD
