Metadata-Version: 2.4
Name: kubedownscaler
Version: 0.4.2
Summary: Scale down and restore Kubernetes deployments and statefulsets
Author: Jonathan Gazeley
Author-email: me@jonathangazeley.com
Requires-Python: >=3.10,<4.0
Classifier: Development Status :: 5 - Production/Stable
Classifier: Operating System :: OS Independent
Classifier: Programming Language :: Python :: 3
Classifier: Programming Language :: Python :: 3.10
Classifier: Programming Language :: Python :: 3.11
Classifier: Programming Language :: Python :: 3.12
Classifier: Programming Language :: Python :: 3.13
Classifier: Programming Language :: Python :: 3.14
Classifier: Topic :: Utilities
Requires-Dist: argparse (>=1.4.0,<2.0.0)
Requires-Dist: kubernetes (>=19.15.0,<20.0.0)
Requires-Dist: termcolor (>=2.3.0,<3.0.0)
Project-URL: Repository, https://github.com/djjudas21/kubedownscaler
